{
  "updated_at": "20260319_061945",
  "elapsed_min": 117.4,
  "poll_count": 106,
  "strategies": {
    "conservative": {
      "strategy": "conservative",
      "label": "\ud83d\udee1\ufe0f\uc548\uc815\ud615",
      "elapsed_min": 117.4,
      "initial": 10000.0,
      "capital": 10000.0,
      "unrealized": 37.9525,
      "equity": 10037.9525,
      "total_pnl": 0.0,
      "roi_pct": 0.0,
      "wins": 0,
      "losses": 0,
      "total_trades": 0,
      "win_rate": 0.0,
      "profit_factor": 0.0,
      "gross_profit": 0.0,
      "gross_loss": 0.0,
      "max_dd_pct": 0.0134,
      "open_positions": 3,
      "equity_series": [
        10000.0,
        10003.32,
        10003.32,
        10002.4,
        10002.46,
        10002.33,
        10002.33,
        10002.62,
        10002.3,
        10002.83,
        10002.9,
        10002.9,
        10003.15,
        10002.99,
        10002.99,
        10003.14,
        10003.09,
        10003.09,
        10002.65,
        10002.65,
        10002.65,
        10002.65,
        10003.04,
        10003.04,
        10002.78,
        10002.78,
        10003.29,
        10003.29,
        10003.29,
        10003.29,
        10003.29,
        10003.59,
        10003.59,
        10003.59,
        10003.59,
        10003.59,
        10003.59,
        10003.59,
        10003.66,
        10003.49,
        10003.49,
        10003.49,
        10003.49,
        10003.11,
        10003.11,
        10002.92,
        10002.92,
        10002.92,
        10003.24,
        10003.24,
        10003.24,
        10003.24,
        10003.63,
        10003.54,
        10003.54,
        10003.54,
        10003.54,
        10002.98,
        10002.98,
        10002.98,
        10002.35,
        10002.35,
        10002.32,
        10002.57,
        10002.57,
        10002.57,
        10002.57,
        10002.57,
        10002.57,
        10002.57,
        10003.17,
        10003.17,
        10003.61,
        10003.42,
        10003.42,
        10003.22,
        10002.97,
        10002.97,
        10002.97,
        10002.97,
        10003.14,
        10003.14,
        10003.14,
        10003.14,
        10003.14,
        10003.3,
        10003.3,
        10003.29,
        10003.29,
        10003.29,
        10003.29,
        10003.29,
        10003.29,
        10036.62,
        10037.07,
        10038.07,
        10038.07,
        10038.07,
        10038.07,
        10038.07,
        10038.07,
        10038.07,
        10038.07,
        10037.87,
        10038.02,
        10037.95
      ],
      "closed_trades": [],
      "copy_ratio": 0.05,
      "max_pos_usdc": 500.0,
      "stop_loss": 5.0,
      "take_profit": 12.0
    },
    "default": {
      "strategy": "default",
      "label": "\u2699\ufe0f\uae30\ubcf8\ud615",
      "elapsed_min": 117.4,
      "initial": 10000.0,
      "capital": 9834.9847,
      "unrealized": -14.3281,
      "equity": 9820.6566,
      "total_pnl": -165.0153,
      "roi_pct": -1.6502,
      "wins": 0,
      "losses": 1,
      "total_trades": 1,
      "win_rate": 0.0,
      "profit_factor": 0.0,
      "gross_profit": 0.0,
      "gross_loss": -165.0153,
      "max_dd_pct": 1.8698,
      "open_positions": 9,
      "equity_series": [
        10000.0,
        10000.05,
        9981.07,
        9827.59,
        9981.24,
        9981.29,
        9981.29,
        9981.29,
        9982.01,
        9981.46,
        9814.65,
        9814.45,
        9814.12,
        9814.01,
        9813.67,
        9813.67,
        9813.43,
        9813.21,
        9813.16,
        9813.21,
        9813.21,
        9813.43,
        9813.4,
        9813.27,
        9813.27,
        9813.52,
        9813.3,
        9813.55,
        9816.08,
        9813.83,
        9813.83,
        9814.06,
        9814.67,
        9814.67,
        9817.18,
        9817.21,
        9816.88,
        9816.71,
        9814.12,
        9814.06,
        9814.18,
        9814.21,
        9814.21,
        9814.1,
        9815.51,
        9815.61,
        9815.63,
        9815.55,
        9815.59,
        9815.32,
        9815.93,
        9816.0,
        9815.96,
        9816.28,
        9816.19,
        9816.03,
        9815.48,
        9818.02,
        9818.69,
        9818.41,
        9815.61,
        9815.06,
        9816.45,
        9816.64,
        9816.69,
        9819.08,
        9819.08,
        9816.74,
        9816.8,
        9819.92,
        9819.95,
        9818.24,
        9815.74,
        9815.74,
        9815.68,
        9818.02,
        9818.6,
        9817.85,
        9815.36,
        9815.19,
        9814.68,
        9814.62,
        9814.57,
        9817.91,
        9815.23,
        9815.35,
        9814.55,
        9814.95,
        9814.95,
        9815.1,
        9814.79,
        9815.25,
        9815.25,
        9815.36,
        9813.1,
        9813.08,
        9814.82,
        9816.49,
        9816.49,
        9816.88,
        9816.88,
        9816.85,
        9816.85,
        9816.85,
        9814.55,
        9814.55
      ],
      "closed_trades": [
        {
          "symbol": "XRP",
          "side": "short",
          "entry": 1.448316,
          "exit": 2.1088,
          "size": 249.84,
          "pnl": -165.0153,
          "pct": -45.6,
          "held_min": 12.3,
          "trader": "Ph9yECGo",
          "reason": "SL"
        }
      ],
      "copy_ratio": 0.18,
      "max_pos_usdc": 500.0,
      "stop_loss": 12.0,
      "take_profit": 25.0
    },
    "balanced": {
      "strategy": "balanced",
      "label": "\u2696\ufe0f\uade0\ud615\ud615",
      "elapsed_min": 117.4,
      "initial": 10000.0,
      "capital": 10000.0,
      "unrealized": 26.648,
      "equity": 10026.648,
      "total_pnl": 0.0,
      "roi_pct": 0.0,
      "wins": 0,
      "losses": 0,
      "total_trades": 0,
      "win_rate": 0.0,
      "profit_factor": 0.0,
      "gross_profit": 0.0,
      "gross_loss": 0.0,
      "max_dd_pct": 0.2684,
      "open_positions": 12,
      "equity_series": [
        10000.0,
        10005.34,
        10016.03,
        10048.34,
        10041.57,
        10040.7,
        10040.71,
        10040.72,
        10041.29,
        10041.98,
        10034.45,
        10034.34,
        10033.89,
        10033.58,
        10032.62,
        10032.77,
        10032.51,
        10032.1,
        10031.5,
        10031.31,
        10031.93,
        10031.53,
        10032.17,
        10032.11,
        10031.69,
        10032.35,
        10032.79,
        10033.39,
        10034.79,
        10033.31,
        10033.21,
        10034.21,
        10035.16,
        10035.12,
        10036.54,
        10036.68,
        10036.15,
        10035.98,
        10034.82,
        10034.57,
        10034.74,
        10034.72,
        10035.6,
        10034.51,
        10034.88,
        10034.73,
        10034.41,
        10034.6,
        10035.15,
        10035.9,
        10036.75,
        10037.36,
        10037.79,
        10038.19,
        10037.0,
        10037.02,
        10036.0,
        10034.91,
        10035.28,
        10034.83,
        10031.73,
        10030.4,
        10032.03,
        10032.54,
        10032.62,
        10032.11,
        10032.18,
        10032.18,
        10032.27,
        10032.52,
        10033.52,
        10032.57,
        10034.62,
        10034.32,
        10034.23,
        10034.11,
        10034.03,
        10033.15,
        10032.55,
        10032.29,
        10032.28,
        10032.25,
        10032.22,
        10032.69,
        10032.68,
        10032.86,
        10032.37,
        10032.58,
        10032.58,
        10032.75,
        10031.59,
        10031.62,
        10031.62,
        10021.89,
        10021.37,
        10023.06,
        10024.03,
        10026.4,
        10026.4,
        10027.01,
        10026.03,
        10026.18,
        10025.74,
        10025.32,
        10026.04,
        10026.65
      ],
      "closed_trades": [],
      "copy_ratio": 0.1,
      "max_pos_usdc": 800.0,
      "stop_loss": 8.0,
      "take_profit": 18.0
    },
    "aggressive": {
      "strategy": "aggressive",
      "label": "\ud83d\ude80\uacf5\uaca9\ud615",
      "elapsed_min": 117.4,
      "initial": 10000.0,
      "capital": 10000.0,
      "unrealized": 172.3133,
      "equity": 10172.3133,
      "total_pnl": 0.0,
      "roi_pct": 0.0,
      "wins": 0,
      "losses": 0,
      "total_trades": 0,
      "win_rate": 0.0,
      "profit_factor": 0.0,
      "gross_profit": 0.0,
      "gross_loss": 0.0,
      "max_dd_pct": 0.796,
      "open_positions": 15,
      "equity_series": [
        10000.0,
        10083.0,
        10170.22,
        10230.87,
        10218.21,
        10213.57,
        10208.39,
        10210.14,
        10211.8,
        10213.91,
        10198.9,
        10198.49,
        10196.57,
        10196.17,
        10193.39,
        10192.04,
        10191.54,
        10189.15,
        10187.7,
        10187.97,
        10189.12,
        10188.38,
        10182.91,
        10180.38,
        10179.62,
        10181.08,
        10181.89,
        10185.51,
        10187.67,
        10185.05,
        10184.85,
        10187.19,
        10191.85,
        10188.03,
        10188.7,
        10190.26,
        10190.63,
        10190.55,
        10188.19,
        10185.88,
        10187.59,
        10187.55,
        10189.47,
        10190.12,
        10190.93,
        10190.67,
        10195.21,
        10195.54,
        10197.26,
        10202.08,
        10204.12,
        10205.29,
        10201.17,
        10204.38,
        10196.79,
        10194.7,
        10192.77,
        10184.69,
        10186.08,
        10183.24,
        10175.02,
        10171.17,
        10174.44,
        10179.45,
        10179.61,
        10177.47,
        10177.56,
        10175.25,
        10175.42,
        10175.92,
        10182.01,
        10185.28,
        10190.58,
        10189.08,
        10188.92,
        10188.66,
        10185.45,
        10190.27,
        10189.15,
        10188.65,
        10194.19,
        10193.23,
        10193.17,
        10190.37,
        10188.2,
        10188.53,
        10187.49,
        10187.68,
        10187.38,
        10185.9,
        10181.24,
        10182.54,
        10182.85,
        10149.43,
        10150.56,
        10159.79,
        10162.49,
        10167.62,
        10173.45,
        10174.83,
        10172.86,
        10173.11,
        10172.22,
        10171.43,
        10171.81,
        10172.31
      ],
      "closed_trades": [],
      "copy_ratio": 0.2,
      "max_pos_usdc": 1500.0,
      "stop_loss": 12.0,
      "take_profit": 35.0
    }
  }
}